LICENSE.txt
README.md
setup.py
adh_deployment_manager/__init__.py
adh_deployment_manager/adh_service.py
adh_deployment_manager/authenticator.py
adh_deployment_manager/commands_factory.py
adh_deployment_manager/config.py
adh_deployment_manager/deployment.py
adh_deployment_manager/job.py
adh_deployment_manager/query.py
adh_deployment_manager/utils.py
adh_deployment_manager.egg-info/PKG-INFO
adh_deployment_manager.egg-info/SOURCES.txt
adh_deployment_manager.egg-info/dependency_links.txt
adh_deployment_manager.egg-info/entry_points.txt
adh_deployment_manager.egg-info/requires.txt
adh_deployment_manager.egg-info/top_level.txt
adh_deployment_manager/commands/__init__.py
adh_deployment_manager/commands/abs_command.py
adh_deployment_manager/commands/deploy.py
adh_deployment_manager/commands/fetch.py
adh_deployment_manager/commands/null.py
adh_deployment_manager/commands/populate.py
adh_deployment_manager/commands/run.py
adh_deployment_manager/commands/update.py
tests/__init__.py
tests/tests_config.py
tests/tests_query.py
tests/tests_utils.py