Metadata-Version: 2.1
Name: adh-deployment-manager
Version: 0.0.1
Summary: Library for interacting with ADH REST API.
Home-page: https://github.com/google/adh-deployment-manager
Author: Google Inc. (gTech gPS CSE team)
Author-email: no-reply@google.com
License: Apache 2.0
Classifier: Programming Language :: Python :: 3
Classifier: Intended Audience :: Developers
Classifier: Topic :: Software Development :: Libraries :: Python Modules
Classifier: Operating System :: OS Independent
Classifier: License :: OSI Approved :: Apache Software License
License-File: LICENSE.txt
